orchestrator/__init__.py
orchestrator/config.py
orchestrator/langchain.py
orchestrator/metrics.py
orchestrator/pricing.py
orchestrator/prometheus_exporter.py
orchestrator/providers/__init__.py
orchestrator/providers/base.py
orchestrator/providers/gigachat.py
orchestrator/providers/mock.py
orchestrator/providers/ollama.py
orchestrator/providers/yandexgpt.py
orchestrator/py.typed
orchestrator/retrieval/__init__.py
orchestrator/retrieval/async_faiss.py
orchestrator/retrieval/base.py
orchestrator/retrieval/errors.py
orchestrator/retrieval/langchain_compat.py
orchestrator/router.py
orchestrator/tokenization.py
orchestrator/validators/__init__.py
orchestrator/validators/base.py
orchestrator/validators/errors.py
orchestrator/validators/gigachat.py
orchestrator/validators/yandexgpt.py
multi_llm_orchestrator-0.9.0.dist-info/METADATA
multi_llm_orchestrator-0.9.0.dist-info/WHEEL
multi_llm_orchestrator-0.9.0.dist-info/licenses/LICENSE
multi_llm_orchestrator-0.9.0.dist-info/RECORD
