Metadata-Version: 2.4
Name: multi-llm-orchestrator
Version: 0.9.0
Summary: Unified interface for Russian LLMs with intelligent routing and fallback
License: MIT
License-File: LICENSE
Keywords: llm,ai,gigachat,yandexgpt,router,orchestrator,russian-ai,fallback,multi-provider
Author: Mikhail Malorod
Author-email: MikhailMalorod@users.noreply.github.com
Requires-Python: >=3.11,<4.0
Classifier: Development Status :: 3 - Alpha
Classifier: Intended Audience :: Developers
Classifier: License :: OSI Approved :: MIT License
Classifier: Programming Language :: Python :: 3
Classifier: Programming Language :: Python :: 3.11
Classifier: Programming Language :: Python :: 3.12
Classifier: Programming Language :: Python :: 3.13
Classifier: Programming Language :: Python :: 3.14
Classifier: Topic :: Scientific/Engineering :: Artificial Intelligence
Classifier: Topic :: Software Development :: Libraries :: Python Modules
Provides-Extra: all
Provides-Extra: langchain
Provides-Extra: retrieval
Requires-Dist: aiohttp (>=3.9.1,<4.0.0)
Requires-Dist: faiss-cpu (>=1.7.4,<2.0.0) ; extra == "retrieval" or extra == "all"
Requires-Dist: httpx (>=0.27.0,<0.28.0)
Requires-Dist: langchain-community (>=0.0.38) ; extra == "retrieval" or extra == "all"
Requires-Dist: langchain-core (>=0.1.0) ; extra == "langchain" or extra == "retrieval" or extra == "all"
Requires-Dist: prometheus-client (>=0.19.0,<0.20.0)
Requires-Dist: pydantic (>=2.5.0,<3.0.0)
Requires-Dist: python-dotenv (>=1.0.0,<2.0.0)
Requires-Dist: pyyaml (>=6.0,<7.0)
Requires-Dist: rich (>=13.7.0,<14.0.0)
Requires-Dist: tiktoken (>=0.12.0,<0.13.0)
Requires-Dist: typer (>=0.9.0,<0.10.0)
Project-URL: Homepage, https://github.com/MikhailMalorod/Multi-LLM-Orchestrator
Project-URL: Repository, https://github.com/MikhailMalorod/Multi-LLM-Orchestrator
